nut/__init__.py
nut/main.py
nut/modules/__init__.py
nut/modules/create.py
nut/modules/exploits.py
nut/modules/export.py
nut/modules/list.py
nut/modules/urls.py
nut/nut.conf
nut/settings.py
nut/utils.py
nessus_utility_toolkit-1.3.0.dist-info/METADATA
nessus_utility_toolkit-1.3.0.dist-info/WHEEL
nessus_utility_toolkit-1.3.0.dist-info/entry_points.txt
nessus_utility_toolkit-1.3.0.dist-info/RECORD
