Metadata-Version: 2.1
Name: nessus-utility-toolkit
Version: 1.3.0
Summary: Toolkit to automate and simplify common tasks involving Nessus
Author: karrni
Author-email: karrni@proton.me
Requires-Python: >=3.9,<4.0
Classifier: Programming Language :: Python :: 3
Classifier: Programming Language :: Python :: 3.9
Classifier: Programming Language :: Python :: 3.10
Classifier: Programming Language :: Python :: 3.11
Requires-Dist: colorama (>=0.4.6,<0.5.0)
Requires-Dist: nessus-py (>=1.2.1,<2.0.0)
Requires-Dist: netaddr (>=0.9.0,<0.10.0)
Requires-Dist: pathvalidate (>=3.2.0,<4.0.0)
Requires-Dist: prettytable (>=3.9.0,<4.0.0)
Requires-Dist: pyyaml (>=6.0.1,<7.0.0)
Requires-Dist: urllib3 (>=2.0.6,<3.0.0)
